bitl/__init__.py
bitl-0.0.1.dist-info/DESCRIPTION.rst
bitl-0.0.1.dist-info/METADATA
bitl-0.0.1.dist-info/RECORD
bitl-0.0.1.dist-info/WHEEL
bitl-0.0.1.dist-info/metadata.json
bitl-0.0.1.dist-info/top_level.txt
