Metadata-Version: 2.0
Name: bitl
Version: 0.0.1
Summary: A package to benchmark multi-armed bandit algorithms
Home-page: https://github.com/tritas/bitl
Author: Aris Tritas
Author-email: aris.tritas@u-psud.fr
License: BSD
Platform: UNKNOWN
